kapla/cli/__main__.py
kapla/cli/app.py
kapla/cli/commands/base.py
kapla/cli/commands/buildx.py
kapla/cli/commands/deps.py
kapla/cli/commands/new.py
kapla/cli/commands/profile.py
kapla/cli/commands/release.py
kapla/cli/defaults/release.config.js
kapla/cli/globals.py
kapla/docker/datatypes.py
kapla_cli-3.6.1.dist-info/entry_points.txt
kapla_cli-3.6.1.dist-info/WHEEL
kapla_cli-3.6.1.dist-info/METADATA
kapla_cli-3.6.1.dist-info/RECORD
