Metadata-Version: 2.1
Name: kapla-cli
Version: 3.6.1
Summary: 
Author: Guillaume Charbonnier
Author-email: guillaume.charbonnier@araymond.com
Requires-Python: >=3.7,<4.0
Classifier: Programming Language :: Python :: 3
Classifier: Programming Language :: Python :: 3.10
Classifier: Programming Language :: Python :: 3.7
Classifier: Programming Language :: Python :: 3.8
Classifier: Programming Language :: Python :: 3.9
Requires-Dist: black
Requires-Dist: commitizen (>=2.0.0,<3.0.0)
Requires-Dist: flake8 (>=4.0.0,<5.0.0)
Requires-Dist: isort (>=5.0.0,<6.0.0)
Requires-Dist: kapla-cli-core (>=3.4)
Requires-Dist: mypy (<1.0.0)
Requires-Dist: pre-commit (>=2.0.0,<3.0.0)
Requires-Dist: pytest (>=6.0.0,<7.0.0)
Requires-Dist: pytest-cov (>=3.0.0,<4.0.0)
Requires-Dist: snakeviz (>=2.0.0,<3.0.0)
Requires-Dist: twine (>=3.0.0,<4.0.0)
Requires-Dist: types-PyYAML (>=6.0.0,<7.0.0)
Requires-Dist: types-pkg-resources (<1.0.0)
